LICENSE.txt
MANIFEST.in
README.md
setup.py
cartesius/__init__.py
cartesius/charts.py
cartesius/colors.py
cartesius/elements.py
cartesius/main.py
cartesius/utils.py
cartesius.egg-info/PKG-INFO
cartesius.egg-info/SOURCES.txt
cartesius.egg-info/dependency_links.txt
cartesius.egg-info/top_level.txt
cartesius/fonts/Oxygen-Regular.ttf