Metadata-Version: 1.0
Name: cartesius
Version: 0.2.9
Summary: Cartesius 2D coordinate system drawing library
Home-page: http://tkrajina.github.com/cartesius/
Author: Tomo Krajina
Author-email: tkrajina@gmail.com
License: Apache License, Version 2.0
Platform: UNKNOWN
